axsdb/__init__.py
axsdb/_version.py
axsdb/cli.py
axsdb/core.py
axsdb/error.py
axsdb/factory.py
axsdb/py.typed
axsdb/typing.py
axsdb/units.py
axsdb-0.0.2.dist-info/METADATA
axsdb-0.0.2.dist-info/WHEEL
axsdb-0.0.2.dist-info/entry_points.txt
axsdb-0.0.2.dist-info/RECORD
