Metadata-Version: 2.4
Name: axsdb
Version: 0.0.2
Summary: An absorption database reader for the Eradiate radiative transfer model.
Author-email: Vincent Leroy <vincent.leroy@rayference.eu>
Requires-Python: >=3.9
Requires-Dist: attrs
Requires-Dist: cachetools
Requires-Dist: netcdf4
Requires-Dist: pint
Requires-Dist: scipy
Requires-Dist: typer
Requires-Dist: xarray
